MANIFEST.in
setup.py
intgraphx/__init__.py
intgraphx.egg-info/PKG-INFO
intgraphx.egg-info/SOURCES.txt
intgraphx.egg-info/dependency_links.txt
intgraphx.egg-info/requires.txt
intgraphx.egg-info/top_level.txt